{
  "fileId": "report_59cc25f3_1771756880",
  "files": [
    {
      "type": "report",
      "path": "uploads/report_59cc25f3_1771756880_report_WhatsApp_Image_2026-02-21_at_15.14.38.jpeg",
      "name": "WhatsApp_Image_2026-02-21_at_15.14.38.jpeg"
    },
    {
      "type": "report",
      "path": "uploads/report_59cc25f3_1771756880_report_WhatsApp_Image_2026-02-21_at_15.14.08.jpeg",
      "name": "WhatsApp_Image_2026-02-21_at_15.14.08.jpeg"
    }
  ],
  "patientData": {
    "name": "John Doe",
    "age": "45",
    "condition": "Diabetes",
    "literacyLevel": "Medium (Educated Patient)",
    "date": "22/02/2026"
  },
  "uploadedAt": "2026-02-22T16:11:20.324679"
}